madore/__init__.py
madore/__main__.py
madore/cli.py
madore/render.py
madore/style.css
madore/renderers/__init__.py
madore/renderers/matplotlib.py
madore/renderers/pandas.py
madore-1.dist-info/LICENSE
madore-1.dist-info/METADATA
madore-1.dist-info/WHEEL
madore-1.dist-info/entry_points.txt
madore-1.dist-info/top_level.txt
madore-1.dist-info/RECORD
