Metadata-Version: 2.1
Name: madore
Version: 1
Requires-Python: >=3.8
License-File: LICENSE
Requires-Dist: mistune
